<?xml version="1.0" encoding="UTF-8"?>
<con:testCase id="daf0300e-9c2c-4acc-a0cc-04c0a61cb2be" failOnError="true" failTestCaseOnErrors="true" keepSession="false" maxResults="0" name="TestCase2" searchProperties="true" xmlns:con="http://eviware.com/soapui/config"><con:settings><con:setting id="daf0300e-9c2c-4acc-a0cc-04c0a61cb2befileName">TestCase2</con:setting></con:settings><con:testStep type="request" id="e6a3aa73-067b-4397-9de1-59b862c96f90" name="Step1"><con:settings/><con:config xsi:type="con:RequestStep" xmlns:xsi="http://www.w3.org/2001/XMLSchema-instance"><con:interface>CalculatorSoap</con:interface><con:operation>Add</con:operation><con:request name="Step1" outgoingWss="" incomingWss="" timeout="" sslKeystore="" useWsAddressing="false" useWsReliableMessaging="false" wssPasswordType="" id="a437cd91-49f5-40b1-98e6-6a07df41ad6d"><con:settings/><con:encoding>UTF-8</con:encoding><con:endpoint>http://www.dneonline.com/calculator.asmx</con:endpoint><con:request><![CDATA[<soapenv:Envelope xmlns:soapenv="http://schemas.xmlsoap.org/soap/envelope/" xmlns:tem="http://tempuri.org/">\r
   <soapenv:Header/>\r
   <soapenv:Body>\r
      <tem:Add>\r
         <tem:intA>11</tem:intA>\r
         <tem:intB>12</tem:intB>\r
      </tem:Add>\r
   </soapenv:Body>\r
</soapenv:Envelope>]]></con:request><con:assertion type="SOAP Response" id="83130ee2-b535-402d-b4ce-fef7156b0b7c" name="SOAP Response"/><con:credentials><con:selectedAuthProfile>No Authorization</con:selectedAuthProfile><con:authType>No Authorization</con:authType></con:credentials><con:jmsConfig JMSDeliveryMode="PERSISTENT"/><con:jmsPropertyConfig/><con:wsaConfig mustUnderstand="NONE" version="200508" action="http://tempuri.org/Add"/><con:wsrmConfig version="1.2"/></con:request></con:config></con:testStep><con:properties/><con:reportParameters/></con:testCase>